{
  "posts": [
    {
      "id": "jwjtrdf9ok",
      "title": "18天快速掌握造航母",
      "content": "航母制造训练营简介"
    },
    {
      "id": "qkijyburrx",
      "title": "18天快速掌握种棉花666",
      "content": "棉花种植技术讲解"
    },
    {
      "id": "5lg3cudppg",
      "title": "18天快速掌握造坦克",
      "content": "坦克制造训练营简介"
    },
    {
      "id": "hxqz5wwxgqe",
      "title": "18天快速掌握造火箭",
      "content": "火箭制造训练营简介"
    },
    {
      "id": "4uwhlu2vh76",
      "title": "18天快速掌握造飞机",
      "content": "飞机制造训练营简介"
    }
  ]
}